zserio/__init__.py
zserio/__main__.py
zserio/array.py
zserio/bitbuffer.py
zserio/bitfield.py
zserio/bitposition.py
zserio/bitreader.py
zserio/bitsizeof.py
zserio/bitwriter.py
zserio/builtin.py
zserio/compiler.py
zserio/cppbind.py
zserio/creator.py
zserio/debugstring.py
zserio/enum.py
zserio/exception.py
zserio/float.py
zserio/hashcode.py
zserio/json.py
zserio/limits.py
zserio/pubsub.py
zserio/py.typed
zserio/serialization.py
zserio/service.py
zserio/typeinfo.py
zserio/walker.py
zserio/compiler/zserio.jar
zserio-2.18.0.dist-info/licenses/LICENSE
zserio-2.18.0.dist-info/METADATA
zserio-2.18.0.dist-info/WHEEL
zserio-2.18.0.dist-info/entry_points.txt
zserio-2.18.0.dist-info/top_level.txt
zserio-2.18.0.dist-info/RECORD
