Metadata-Version: 2.4
Name: zserio
Version: 2.18.0
Summary: Zserio runtime with compiler.
Home-page: https://github.com/ndsev/zserio-pypi
Author: Navigation Data Standard e.V.
Author-email: support@nds-association.org
License: BSD-3 Clause
Classifier: Programming Language :: Python :: 3
Classifier: Operating System :: OS Independent
Classifier: License :: OSI Approved :: BSD License
Requires-Python: >=3.8
License-File: LICENSE
Dynamic: author
Dynamic: author-email
Dynamic: classifier
Dynamic: description
Dynamic: description-content-type
Dynamic: home-page
Dynamic: license
Dynamic: license-file
Dynamic: requires-python
Dynamic: summary
